{
  "parent": "minecraft:recipes/root",
  "rewards": {
    "recipes": [
      "stellamecanics:solarium_block"
    ]
  },
  "criteria": {
    "unlock": {
      "trigger": "minecraft:inventory_changed",
      "conditions": {
        "items": [
          {
            "item": "stellamecanics:solarium_ingot"
          }
        ]
      }
    },
    "has_the_recipe": {
      "trigger": "minecraft:recipe_unlocked",
      "conditions": {
        "recipe": "stellamecanics:solarium_block"
      }
    }
  },
  "requirements": [
    [
      "unlock",
      "has_the_recipe"
    ]
  ]
}